adminfilters/__init__.py
adminfilters/apps.py
adminfilters/autocomplete.py
adminfilters/checkbox.py
adminfilters/checks.py
adminfilters/combo.py
adminfilters/compat.py
adminfilters/dates.py
adminfilters/dj.py
adminfilters/extra.py
adminfilters/filters.py
adminfilters/json_filter.py
adminfilters/mixin.py
adminfilters/multiselect.py
adminfilters/num.py
adminfilters/py.typed
adminfilters/querystring.py
adminfilters/radio.py
adminfilters/utils.py
adminfilters/value.py
adminfilters/version.py
adminfilters/depot/__init__.py
adminfilters/depot/admin.py
adminfilters/depot/apps.py
adminfilters/depot/models.py
adminfilters/depot/widget.py
adminfilters/depot/migrations/0001_initial.py
adminfilters/depot/migrations/0002_migration.py
adminfilters/depot/migrations/0003_alter_storedfilter_id.py
adminfilters/depot/migrations/0004_alter_storedfilter_query_string.py
adminfilters/depot/migrations/__init__.py
adminfilters/depot/templates/adminfilters/widget.html
adminfilters/static/adminfilters/adminfilters.css
adminfilters/static/adminfilters/adminfilters.css.map
adminfilters/static/adminfilters/adminfilters.min.css
adminfilters/static/adminfilters/adminfilters.min.css.map
adminfilters/static/adminfilters/adminfilters.scss
adminfilters/static/adminfilters/autocomplete.js
adminfilters/static/adminfilters/autocomplete.min.js
adminfilters/static/adminfilters/depot.js
adminfilters/static/adminfilters/depot.min.js
adminfilters/static/adminfilters/dj.js
adminfilters/static/adminfilters/dj.min.js
adminfilters/static/adminfilters/jsonfilter.js
adminfilters/static/adminfilters/jsonfilter.min.js
adminfilters/static/adminfilters/querystring.js
adminfilters/static/adminfilters/querystring.min.js
adminfilters/static/adminfilters/value.js
adminfilters/static/adminfilters/value.min.js
adminfilters/templates/adminfilters/_attrs.html
adminfilters/templates/adminfilters/_wrapper.html
adminfilters/templates/adminfilters/autocomplete.html
adminfilters/templates/adminfilters/checkbox.html
django_adminfilters-2.7.dist-info/METADATA
django_adminfilters-2.7.dist-info/WHEEL
django_adminfilters-2.7.dist-info/licenses/AUTHORS
django_adminfilters-2.7.dist-info/licenses/LICENSE
django_adminfilters-2.7.dist-info/RECORD
