Metadata-Version: 2.4
Name: django-adminfilters
Version: 2.7
Summary: Collection of Django Admin filters
Project-URL: Documentation, https://github.com/saxix/django-adminfilters
Project-URL: Homepage, https://github.com/saxix/django-adminfilters
License-File: AUTHORS
License-File: LICENSE
Classifier: Environment :: Web Environment
Classifier: Framework :: Django
Classifier: Framework :: Django :: 4.2
Classifier: Framework :: Django :: 5.2
Classifier: Intended Audience :: Developers
Classifier: License :: OSI Approved :: BSD License
Classifier: Operating System :: OS Independent
Classifier: Programming Language :: Python :: 3 :: Only
Classifier: Programming Language :: Python :: 3.10
Classifier: Programming Language :: Python :: 3.11
Classifier: Programming Language :: Python :: 3.12
Classifier: Programming Language :: Python :: 3.13
Classifier: Topic :: Software Development :: Libraries :: Application Frameworks
Classifier: Topic :: Software Development :: Libraries :: Python Modules
Requires-Python: >=3.10
Requires-Dist: django-stubs-ext>=5.1.3
Requires-Dist: django-stubs>=5.1.3
